python_clustering/__init__.py
python_clustering/datasets/D31.arff
python_clustering/datasets/atom.arff
python_clustering/datasets/banana.arff
python_clustering/datasets/circle.arff
python_clustering/datasets/cpu.arff
python_clustering/datasets/gaussians1.arff
python_clustering/jsons/catalogue_info.json
python_clustering/jsons/dataset_info.json
python_clustering/python_clustering.py
python_clustering/utilities/__init__.py
python_clustering/utilities/anomaly_detection.py
python_clustering/utilities/catalogue_utilities.py
python_clustering/utilities/dataset_utilities.py
python_clustering/utilities/preprocessing_utilities.py
python_clustering/utilities/read_utilities.py
python_clustering-1.3.0.dist-info/LICENSE
python_clustering-1.3.0.dist-info/METADATA
python_clustering-1.3.0.dist-info/WHEEL
python_clustering-1.3.0.dist-info/RECORD
