Metadata-Version: 2.1
Name: python-clustering
Version: 1.3.0
Summary: Intuitive access to clustering datasets, methods and tasks
Home-page: https://pypi.org/project/python-clustering/
License: MIT
Keywords: clustering,datasets
Author: Ivan Reznikov
Author-email: ivanreznikov@gmail.com
Requires-Python: >=3.8,<3.12
Classifier: License :: OSI Approved :: MIT License
Classifier: Programming Language :: Python :: 3
Classifier: Programming Language :: Python :: 3.8
Classifier: Programming Language :: Python :: 3.9
Classifier: Programming Language :: Python :: 3.10
Classifier: Programming Language :: Python :: 3.11
Requires-Dist: arff (>=0.9,<0.10)
Requires-Dist: llvmlite (>=0.39.1,<0.40.0)
Requires-Dist: matplotlib (>=3.7.1,<4.0.0)
Requires-Dist: pandas (>=1.5.3,<2.0.0)
Requires-Dist: pyod (>=1.0.7,<2.0.0)
Requires-Dist: requests (>=2.28.2,<3.0.0)
Requires-Dist: scipy (>=1.10.1,<2.0.0)
Requires-Dist: tensorflow (>=2.11.0,<3.0.0)
Requires-Dist: tqdm (>=4.65.0,<5.0.0)
Project-URL: Repository, https://github.com/IvanReznikov/python-clustering
